curio_http_server/__init__.py
curio_http_server/forms.py
curio_http_server/handlers.py
curio_http_server/headers.py
curio_http_server/request.py
curio_http_server/response.py
curio_http_server/router.py
curio_http_server/server11.py
curio_http_server-0.2.dist-info/LICENSE
curio_http_server-0.2.dist-info/METADATA
curio_http_server-0.2.dist-info/WHEEL
curio_http_server-0.2.dist-info/top_level.txt
curio_http_server-0.2.dist-info/RECORD
